{
	"codeNames": {
		"0.0": "Perseus Amber",
		"0.1": "Bronze Marklar",
		"0.2": "Scandium Aurora",
		"0.3": "Dakar Snarfman",
		"0.4": "Manila Quadra",
		"0.5": "Aluminium Fafnir",
		"0.6": "Nicosia Autobahn",
		"0.7": "Bissau Cowpuncher",
		"0.8": "Rabat Cyberpup",
		"0.9": "Brazzaville Edison",
		"1.0": "Platinum Uninorth",
		"1.1": "Tokyo Artemis",
		"1.2": "Bishtek Sphere",
		"1.3": "Honiara Nimitz",
		"1.4": "Steel Faraday",
		"1.5": "Manama Denali",
		"1.6": "Pretoria Spin",
		"1.7": "Cadmium Moroni",
		"1.8": "Astana Tomcat",
		"1.9": "Amman Epic",
		"2.0": "Mercury Shuffle",
		"2.1": "Gaborone Sonata",
		"2.2": "Jakarta Catalyst",
		"2.3": "Lead Riyadh",
		"2.4": "Vanadium Optima",
		"2.5": "Cobalt Freeport",
		"2.6": "Niamey Goldstar",
		"2.7": "Tantalum Rainmaker",
		"2.8": "Andorra Casper",
		"2.9": "Polonium Esprit",
		"3.0": "Copper Oceanic",
		"3.1": "Monrovia Starlight",
		"3.2": "Lilongwe Photon",
		"3.3": "Taipei Hyperbolic",
		"3.4": "Iridium Betelgeuse",
		"3.5": "Maputo Darwin",
		"3.6": "Castries Apollo",
		"3.7": "Vilnius Fidelity",
		"3.8": "Lithium Pislo",
		"3.9": "Bamako Slingshot",
		"4.0": "Nickel Molokini",
		"4.1": "Nucalc Figaro",
		"4.2": "Sofia Primus",
		"4.3": "Astana Twister",
		"4.4": "Kampala Sousa",
		"4.5": "Tuvalu Powersurge",
		"4.6": "Vientiane Chimera",
		"4.7": "Zirconium Tempes",
		"4.8": "Luanda Tailspin",
		"4.9": "Djibouti Evolution",
		"5.0": "Titanium Inertia",
		"5.1": "Praia Barleycorn",
		"5.2": "Bangui Therblig",
		"5.3": "Maseru Dash",
		"5.4": "Kelvin Tunis",
		"5.5": "Span Pottle",
		"5.6": "Trident Mho",
		"5.7": "McKendrick Dol",
		"5.8": "Babylon Palm",
		"5.9": "Coyote Plato",
		"6.0": "Xenon Whitehorse",
		"6.1": "Whisper Brich",
		"6.2": "Pegasus Latinum",
		"6.3": "Cirrus Exige",
		"6.4": "Goldeneye Acrylic",
		"6.5": "Steelhead Smaragdine",
		"6.6": "Spark Azuline",
		"6.7": "Matrix Touchdown",
		"6.8": "Cardinal Melanic",
		"6.9": "Stinger Talisker",
		"7.0": "Merlin Heliotrope",
		"7.1": "Haiku Elise",
		"7.2": "Fusion Russet",
		"7.3": "Marvel Glaucous",
		"7.4": "Katmai Impala",
		"7.5": "Wheaten Castaneous",
		"7.6": "Kagera Zinnober",
		"7.7": "Virid Wallflower",
		"7.8": "Viper Flavescent",
		"7.9": "Hailstorm Ren",
		"8.0": "Virescent Spitfire",
		"8.1": "Luna Cesious",
		"8.2": "Morpheus Argent",
		"8.3": "Puniceous Acadia",
		"8.4": "Gosling Cinnabar",
		"8.5": "Cormorant Smalt",
		"8.6": "Flammeous Pacific",
		"8.7": "Omega Sapphire",
		"8.8": "Zydeco Jessamy",
		"8.9": "Sinopia Vulture",
		"9.0": "Talisman Airstream",
		"9.1": "Dragonkid Malibu",
		"9.2": "Dharma Slate",
		"9.3": "Testaceous Amiga",
		"9.4": "Perestroika Avatar",
		"9.5": "Sheffield Ianthine",
		"9.6": "Raven Wolfpack",
		"9.7": "Niveous Speedracer",
		"9.8": "Cayman Arpeggiator",
		"9.9": "Purpureal Symphony",
		"10.0": "Tiberius Epic"
	},
	"patchNames": {
		"1": "Saiga",
		"2": "Ithomiid",
		"3": "Pangolin",
		"4": "Tayra",
		"5": "Uromastix",
		"6": "Anoa",
		"7": "Malbrouck",
		"8": "Balbul",
		"9": "Zokor"
	}
}

